pose_detection/__init__.py
pose_detection/pose_detector.py
pose_detection/pose_model_creator.py
pose_detection-0.1.2.dist-info/METADATA
pose_detection-0.1.2.dist-info/WHEEL
pose_detection-0.1.2.dist-info/top_level.txt
pose_detection-0.1.2.dist-info/RECORD
